{
  "id": 43,
  "seed": "ebc500d2-e707-41be-baf3-96171fd9d697",
  "leader": "Gucury Mk XVIII",
  "colour": 0,
  "value": "0.701",
  "drones": [
    {
      "seed": "ebc500d2-e707-41be-baf3-96171fd9d697",
      "name": "Gucury Mk XVIII",
      "weapon": 4,
      "gimbal": 3,
      "steering": 4,
      "thruster": 1,
      "chassis": 4,
      "scanner": 4,
      "colour": 0,
      "skewMod": 0,
      "skew": 1,
      "value": "0.789",
      "weaponNormal": "1.000",
      "thrusterNormal": "0.400",
      "steeringNormal": "0.833",
      "chassisNormal": "1.000",
      "gimbalNormal": "0.667",
      "scannerNormal": "0.833"
    },
    {
      "seed": "ebc500d2-e707-41be-baf3-96171fd9d697",
      "name": "Qephus Mk LV",
      "weapon": 3,
      "gimbal": 0,
      "steering": 1,
      "thruster": 4,
      "chassis": 2,
      "scanner": 4,
      "colour": 0,
      "skewMod": 0,
      "skew": 1,
      "value": "0.622",
      "weaponNormal": "0.800",
      "thrusterNormal": "1.000",
      "steeringNormal": "0.333",
      "chassisNormal": "0.600",
      "gimbalNormal": "0.167",
      "scannerNormal": "0.833"
    },
    {
      "seed": "ebc500d2-e707-41be-baf3-96171fd9d697",
      "name": "Sestea",
      "weapon": 4,
      "gimbal": 5,
      "steering": 1,
      "thruster": 0,
      "chassis": 3,
      "scanner": 0,
      "colour": 0,
      "skewMod": 0,
      "skew": 1,
      "value": "0.583",
      "weaponNormal": "1.000",
      "thrusterNormal": "0.200",
      "steeringNormal": "0.333",
      "chassisNormal": "0.800",
      "gimbalNormal": "1.000",
      "scannerNormal": "0.167"
    },
    {
      "seed": "ebc500d2-e707-41be-baf3-96171fd9d697",
      "name": "Tunov Mk XXXIV",
      "weapon": 4,
      "gimbal": 2,
      "steering": 1,
      "thruster": 0,
      "chassis": 1,
      "scanner": 4,
      "colour": 0,
      "skewMod": 0,
      "skew": 1,
      "value": "0.544",
      "weaponNormal": "1.000",
      "thrusterNormal": "0.200",
      "steeringNormal": "0.333",
      "chassisNormal": "0.400",
      "gimbalNormal": "0.500",
      "scannerNormal": "0.833"
    },
    {
      "seed": "ebc500d2-e707-41be-baf3-96171fd9d697",
      "name": "Feliv",
      "weapon": 0,
      "gimbal": 3,
      "steering": 1,
      "thruster": 3,
      "chassis": 1,
      "scanner": 2,
      "colour": 0,
      "skewMod": 0,
      "skew": 1,
      "value": "0.483",
      "weaponNormal": "0.200",
      "thrusterNormal": "0.800",
      "steeringNormal": "0.333",
      "chassisNormal": "0.400",
      "gimbalNormal": "0.667",
      "scannerNormal": "0.500"
    },
    {
      "seed": "ebc500d2-e707-41be-baf3-96171fd9d697",
      "name": "Lutania Mk LXXXVIII",
      "weapon": 0,
      "gimbal": 2,
      "steering": 3,
      "thruster": 3,
      "chassis": 1,
      "scanner": 1,
      "colour": 0,
      "skewMod": 0,
      "skew": 1,
      "value": "0.483",
      "weaponNormal": "0.200",
      "thrusterNormal": "0.800",
      "steeringNormal": "0.667",
      "chassisNormal": "0.400",
      "gimbalNormal": "0.500",
      "scannerNormal": "0.333"
    }
  ]
}
