{
  "id": 84,
  "seed": "ffe598db-0a74-4f6e-893c-80aa6745a53f",
  "leader": "Qerilia",
  "colour": 1,
  "value": "0.686",
  "drones": [
    {
      "seed": "ffe598db-0a74-4f6e-893c-80aa6745a53f",
      "name": "Qerilia",
      "weapon": 2,
      "gimbal": 2,
      "steering": 2,
      "thruster": 4,
      "chassis": 3,
      "scanner": 5,
      "colour": 1,
      "skewMod": 0,
      "skew": 1,
      "value": "0.733",
      "weaponNormal": "0.600",
      "thrusterNormal": "1.000",
      "steeringNormal": "0.500",
      "chassisNormal": "0.800",
      "gimbalNormal": "0.500",
      "scannerNormal": "1.000"
    },
    {
      "seed": "ffe598db-0a74-4f6e-893c-80aa6745a53f",
      "name": "Jaturn",
      "weapon": 2,
      "gimbal": 3,
      "steering": 3,
      "thruster": 4,
      "chassis": 3,
      "scanner": 0,
      "colour": 1,
      "skewMod": 0,
      "skew": 1,
      "value": "0.650",
      "weaponNormal": "0.600",
      "thrusterNormal": "1.000",
      "steeringNormal": "0.667",
      "chassisNormal": "0.800",
      "gimbalNormal": "0.667",
      "scannerNormal": "0.167"
    },
    {
      "seed": "ffe598db-0a74-4f6e-893c-80aa6745a53f",
      "name": "Palia v7.83",
      "weapon": 1,
      "gimbal": 3,
      "steering": 3,
      "thruster": 2,
      "chassis": 2,
      "scanner": 2,
      "colour": 1,
      "skewMod": 0,
      "skew": 1,
      "value": "0.572",
      "weaponNormal": "0.400",
      "thrusterNormal": "0.600",
      "steeringNormal": "0.667",
      "chassisNormal": "0.600",
      "gimbalNormal": "0.667",
      "scannerNormal": "0.500"
    },
    {
      "seed": "ffe598db-0a74-4f6e-893c-80aa6745a53f",
      "name": "Nelara v49.59",
      "weapon": 3,
      "gimbal": 3,
      "steering": 1,
      "thruster": 3,
      "chassis": 0,
      "scanner": 2,
      "colour": 1,
      "skewMod": 0,
      "skew": 1,
      "value": "0.550",
      "weaponNormal": "0.800",
      "thrusterNormal": "0.800",
      "steeringNormal": "0.333",
      "chassisNormal": "0.200",
      "gimbalNormal": "0.667",
      "scannerNormal": "0.500"
    },
    {
      "seed": "ffe598db-0a74-4f6e-893c-80aa6745a53f",
      "name": "Vucury v7.1",
      "weapon": 1,
      "gimbal": 2,
      "steering": 0,
      "thruster": 2,
      "chassis": 4,
      "scanner": 2,
      "colour": 1,
      "skewMod": 0,
      "skew": 1,
      "value": "0.528",
      "weaponNormal": "0.400",
      "thrusterNormal": "0.600",
      "steeringNormal": "0.167",
      "chassisNormal": "1.000",
      "gimbalNormal": "0.500",
      "scannerNormal": "0.500"
    },
    {
      "seed": "ffe598db-0a74-4f6e-893c-80aa6745a53f",
      "name": "Lewei",
      "weapon": 0,
      "gimbal": 0,
      "steering": 1,
      "thruster": 0,
      "chassis": 3,
      "scanner": 3,
      "colour": 1,
      "skewMod": 0,
      "skew": 1,
      "value": "0.395",
      "weaponNormal": "0.200",
      "thrusterNormal": "0.200",
      "steeringNormal": "0.333",
      "chassisNormal": "0.800",
      "gimbalNormal": "0.167",
      "scannerNormal": "0.667"
    }
  ]
}
