{
  "id": 98,
  "seed": "efcae47b-f68f-465d-bb1a-b5e562a1cda0",
  "leader": "Xecury",
  "colour": 3,
  "value": "0.685",
  "drones": [
    {
      "seed": "efcae47b-f68f-465d-bb1a-b5e562a1cda0",
      "name": "Xecury",
      "weapon": 2,
      "gimbal": 4,
      "steering": 2,
      "thruster": 4,
      "chassis": 2,
      "scanner": 5,
      "colour": 3,
      "skewMod": 0,
      "skew": 1,
      "value": "0.756",
      "weaponNormal": "0.600",
      "thrusterNormal": "1.000",
      "steeringNormal": "0.500",
      "chassisNormal": "0.600",
      "gimbalNormal": "0.833",
      "scannerNormal": "1.000"
    },
    {
      "seed": "efcae47b-f68f-465d-bb1a-b5e562a1cda0",
      "name": "Mapra",
      "weapon": 1,
      "gimbal": 5,
      "steering": 0,
      "thruster": 4,
      "chassis": 3,
      "scanner": 4,
      "colour": 3,
      "skewMod": 0,
      "skew": 1,
      "value": "0.700",
      "weaponNormal": "0.400",
      "thrusterNormal": "1.000",
      "steeringNormal": "0.167",
      "chassisNormal": "0.800",
      "gimbalNormal": "1.000",
      "scannerNormal": "0.833"
    },
    {
      "seed": "efcae47b-f68f-465d-bb1a-b5e562a1cda0",
      "name": "Jawei v28.11",
      "weapon": 2,
      "gimbal": 3,
      "steering": 3,
      "thruster": 0,
      "chassis": 2,
      "scanner": 2,
      "colour": 3,
      "skewMod": 0,
      "skew": 1,
      "value": "0.539",
      "weaponNormal": "0.600",
      "thrusterNormal": "0.200",
      "steeringNormal": "0.667",
      "chassisNormal": "0.600",
      "gimbalNormal": "0.667",
      "scannerNormal": "0.500"
    },
    {
      "seed": "efcae47b-f68f-465d-bb1a-b5e562a1cda0",
      "name": "Wepra",
      "weapon": 0,
      "gimbal": 1,
      "steering": 2,
      "thruster": 4,
      "chassis": 0,
      "scanner": 3,
      "colour": 3,
      "skewMod": 0,
      "skew": 1,
      "value": "0.483",
      "weaponNormal": "0.200",
      "thrusterNormal": "1.000",
      "steeringNormal": "0.500",
      "chassisNormal": "0.200",
      "gimbalNormal": "0.333",
      "scannerNormal": "0.667"
    },
    {
      "seed": "efcae47b-f68f-465d-bb1a-b5e562a1cda0",
      "name": "Leliv",
      "weapon": 2,
      "gimbal": 0,
      "steering": 3,
      "thruster": 1,
      "chassis": 0,
      "scanner": 4,
      "colour": 3,
      "skewMod": 0,
      "skew": 1,
      "value": "0.478",
      "weaponNormal": "0.600",
      "thrusterNormal": "0.400",
      "steeringNormal": "0.667",
      "chassisNormal": "0.200",
      "gimbalNormal": "0.167",
      "scannerNormal": "0.833"
    },
    {
      "seed": "efcae47b-f68f-465d-bb1a-b5e562a1cda0",
      "name": "Telea",
      "weapon": 1,
      "gimbal": 0,
      "steering": 1,
      "thruster": 3,
      "chassis": 2,
      "scanner": 2,
      "colour": 3,
      "skewMod": 0,
      "skew": 1,
      "value": "0.467",
      "weaponNormal": "0.400",
      "thrusterNormal": "0.800",
      "steeringNormal": "0.333",
      "chassisNormal": "0.600",
      "gimbalNormal": "0.167",
      "scannerNormal": "0.500"
    }
  ]
}
