[{"uid":"04zk41","number":"#0133","squadron":"Squadron Felea","highScore":1567900,"rank":47,"width":800,"height":800},{"uid":"tqoDGW","number":"#0130","squadron":"Squadron Doruta","highScore":1342500,"rank":41,"width":800,"height":800},{"uid":"eHpCkO","number":"#0122","squadron":"Squadron Wanope","highScore":1262800,"rank":38,"width":800,"height":800},{"uid":"cGqVD1","number":"#0128","squadron":"Squadron Xetune","highScore":1262800,"rank":38,"width":800,"height":800},{"uid":"HGKEur","number":"#0019","squadron":"Squadron Iavis v40.72","highScore":1257500,"rank":38,"width":800,"height":800},{"uid":"2wYRMm","number":"#0102","squadron":"Squadron Huyama","highScore":1257500,"rank":38,"width":800,"height":800},{"uid":"1vs4QI","number":"#0081","squadron":"Squadron Wustea Mk LXXXVI","highScore":1252800,"rank":38,"width":800,"height":800},{"uid":"HNI0k9","number":"#0055","squadron":"Squadron Sulara v35.90","highScore":1093300,"rank":33,"width":800,"height":800},{"uid":"5wLm1V","number":"#0147","squadron":"Squadron Totera","highScore":935900,"rank":29,"width":800,"height":800},{"uid":"kdodKw","number":"#0142","squadron":"Squadron Nuthea","highScore":685300,"rank":21,"width":800,"height":800},{"uid":"S73K9Q","number":"#0124","squadron":"Squadron Fanov v33.40","highScore":659900,"rank":20,"width":800,"height":800},{"uid":"qRsUzc","number":"#0013","squadron":"Squadron Tewei v11.69","highScore":653800,"rank":20,"width":800,"height":800},{"uid":"BCjqbj","number":"#0017","squadron":"Squadron Wonus","highScore":648700,"rank":20,"width":800,"height":800},{"uid":"nzf3ce","number":"#0119","squadron":"Squadron Xunus Mk XII","highScore":648200,"rank":20,"width":800,"height":800},{"uid":"tMAxh5","number":"#0116","squadron":"Squadron Soria","highScore":626500,"rank":19,"width":800,"height":800},{"uid":"NVnVUl","number":"#0087","squadron":"Squadron Doyama Mk VII","highScore":625500,"rank":19,"width":800,"height":800},{"uid":"yhmB6r","number":"#0037","squadron":"Squadron Decarro","highScore":622100,"rank":19,"width":800,"height":800},{"uid":"ibG3YG","number":"#0031","squadron":"Squadron Ianov","highScore":620600,"rank":19,"width":800,"height":800},{"uid":"HuSxpz","number":"#0145","squadron":"Squadron Yolia v39.2","highScore":620200,"rank":19,"width":800,"height":800},{"uid":"qU3mMd","number":"#0135","squadron":"Squadron Durus v12.47","highScore":615500,"rank":19,"width":800,"height":800},{"uid":"fGA3uo","number":"#0028","squadron":"Squadron Senus Mk XLIX","highScore":614300,"rank":19,"width":800,"height":800},{"uid":"XjuGTm","number":"#0043","squadron":"Squadron Dayama","highScore":614300,"rank":19,"width":800,"height":800},{"uid":"EXIWEH","number":"#0114","squadron":"Squadron Negantu","highScore":614300,"rank":19,"width":800,"height":800},{"uid":"zAMfHr","number":"#0030","squadron":"Squadron Yenus","highScore":614200,"rank":19,"width":800,"height":800},{"uid":"goKBfC","number":"#0103","squadron":"Squadron Xotune v29.73","highScore":610700,"rank":19,"width":800,"height":800},{"uid":"VvS0uh","number":"#0021","squadron":"Squadron Selea","highScore":609900,"rank":19,"width":800,"height":800},{"uid":"L7IqeG","number":"#0083","squadron":"Squadron Hunus v28.9","highScore":609900,"rank":19,"width":800,"height":800},{"uid":"JngY7Y","number":"#0149","squadron":"Squadron Futurn Mk LXXIX","highScore":609500,"rank":19,"width":800,"height":800},{"uid":"qVAuLr","number":"#0035","squadron":"Squadron Haruta Mk XLIX","highScore":609200,"rank":19,"width":800,"height":800},{"uid":"rZyFNX","number":"#0095","squadron":"Squadron Rugawa","highScore":608500,"rank":19,"width":800,"height":800},{"uid":"3fCJIA","number":"#0148","squadron":"Squadron Juter Mk LXVII","highScore":608500,"rank":19,"width":800,"height":800},{"uid":"xtdsxo","number":"#0152","squadron":"Squadron Koturn","highScore":608300,"rank":19,"width":800,"height":800},{"uid":"o2QHl1","number":"#0111","squadron":"Squadron Herilia v14.82","highScore":604800,"rank":19,"width":800,"height":800},{"uid":"uQgtPs","number":"#0120","squadron":"Squadron Waria v41.6","highScore":604800,"rank":19,"width":800,"height":800},{"uid":"GJiE62","number":"#0048","squadron":"Squadron Yayama","highScore":604700,"rank":19,"width":800,"height":800},{"uid":"y4An4u","number":"#0136","squadron":"Squadron Tuvis","highScore":598800,"rank":19,"width":800,"height":800},{"uid":"xPn7aG","number":"#0074","squadron":"Squadron Petania Mk LXXXVII","highScore":587400,"rank":18,"width":800,"height":800},{"uid":"DYq0Zg","number":"#0125","squadron":"Squadron Soter v3.44","highScore":587400,"rank":18,"width":800,"height":800},{"uid":"eOtbSo","number":"#0085","squadron":"Squadron Fupra","highScore":587100,"rank":18,"width":800,"height":800},{"uid":"iJ0LX6","number":"#0076","squadron":"Squadron Qater","highScore":580300,"rank":18,"width":800,"height":800},{"uid":"GpKBWI","number":"#0113","squadron":"Squadron Kunope","highScore":575900,"rank":18,"width":800,"height":800},{"uid":"pTe6bQ","number":"#0053","squadron":"Squadron Zostea","highScore":476400,"rank":15,"width":800,"height":800},{"uid":"qhCeXi","number":"#0071","squadron":"Squadron Secarro","highScore":463400,"rank":14,"width":800,"height":800},{"uid":"miyvqz","number":"#0064","squadron":"Squadron Zoclite","highScore":458800,"rank":14,"width":800,"height":800},{"uid":"oUVBMZ","number":"#0056","squadron":"Squadron Wahiri Mk LXXIV","highScore":455700,"rank":14,"width":800,"height":800},{"uid":"ENy1vV","number":"#0106","squadron":"Squadron Jatania","highScore":455700,"rank":14,"width":800,"height":800},{"uid":"ACJYxl","number":"#0110","squadron":"Squadron Keclite","highScore":455700,"rank":14,"width":800,"height":800},{"uid":"jyfcTs","number":"#0107","squadron":"Squadron Danov","highScore":450600,"rank":14,"width":800,"height":800},{"uid":"LX7vyO","number":"#0096","squadron":"Squadron Funerth","highScore":450400,"rank":14,"width":800,"height":800},{"uid":"w2vMWc","number":"#0138","squadron":"Squadron Bowei","highScore":415500,"rank":13,"width":800,"height":800},{"uid":"6aCaIz","number":"#0088","squadron":"Squadron Julea","highScore":403900,"rank":13,"width":800,"height":800},{"uid":"LwOzge","number":"#0080","squadron":"Squadron Fuwei","highScore":391400,"rank":12,"width":800,"height":800},{"uid":"SBRwSK","number":"#0153","squadron":"Squadron Mustea Mk XIII","highScore":391400,"rank":12,"width":800,"height":800},{"uid":"7e4lcG","number":"#0090","squadron":"Squadron Gohiri","highScore":390000,"rank":12,"width":800,"height":800},{"uid":"vpqxvh","number":"#0082","squadron":"Squadron Qaturn","highScore":389100,"rank":12,"width":800,"height":800},{"uid":"4PkKKQ","number":"#0002","squadron":"Squadron Nonia","highScore":387800,"rank":12,"width":800,"height":800},{"uid":"FCJuQl","number":"#0151","squadron":"Squadron Iutov","highScore":385800,"rank":12,"width":800,"height":800},{"uid":"lSPjeg","number":"#0007","squadron":"Squadron Nostea","highScore":384500,"rank":12,"width":800,"height":800},{"uid":"EcP8Vy","number":"#0094","squadron":"Squadron Monus","highScore":381900,"rank":12,"width":800,"height":800},{"uid":"fNDrcR","number":"#0118","squadron":"Squadron Pucarro","highScore":372000,"rank":12,"width":800,"height":800},{"uid":"3O71As","number":"#0150","squadron":"Squadron Nunerth","highScore":361400,"rank":11,"width":800,"height":800},{"uid":"jncPoe","number":"#0062","squadron":"Squadron Nanov","highScore":360800,"rank":11,"width":800,"height":800},{"uid":"6WrwsC","number":"#0137","squadron":"Squadron Juzuno v16.41","highScore":359200,"rank":11,"width":800,"height":800},{"uid":"gBbhZ8","number":"#0112","squadron":"Squadron Matania","highScore":313800,"rank":10,"width":800,"height":800},{"uid":"P0WXSG","number":"#0049","squadron":"Squadron Ronus v28.11","highScore":296200,"rank":9,"width":800,"height":800},{"uid":"NSj1ah","number":"#0144","squadron":"Squadron Muhiri v31.23","highScore":290900,"rank":9,"width":800,"height":800},{"uid":"YIorHX","number":"#0108","squadron":"Squadron Getis","highScore":288900,"rank":9,"width":800,"height":800},{"uid":"e9U06U","number":"#0001","squadron":"Squadron Gaphus","highScore":285700,"rank":9,"width":800,"height":800},{"uid":"0krj2U","number":"#0129","squadron":"Squadron Peter","highScore":285100,"rank":9,"width":800,"height":800},{"uid":"DBYUqa","number":"#0020","squadron":"Squadron Humia","highScore":283200,"rank":9,"width":800,"height":800},{"uid":"sODKD2","number":"#0058","squadron":"Squadron Guthea","highScore":271700,"rank":8,"width":800,"height":800},{"uid":"DXyNZD","number":"#0123","squadron":"Squadron Fatera","highScore":271700,"rank":8,"width":800,"height":800},{"uid":"FmU6vE","number":"#0057","squadron":"Squadron Ienov","highScore":266900,"rank":8,"width":800,"height":800},{"uid":"4SG5GJ","number":"#0036","squadron":"Squadron Tenia","highScore":255200,"rank":8,"width":800,"height":800},{"uid":"qzTFFP","number":"#0034","squadron":"Squadron Pucury v46.28","highScore":196100,"rank":6,"width":800,"height":800},{"uid":"9PYAY3","number":"#0091","squadron":"Squadron Qalea","highScore":191100,"rank":6,"width":800,"height":800},{"uid":"mI2RbW","number":"#0105","squadron":"Squadron Nalea v36.5","highScore":191100,"rank":6,"width":800,"height":800},{"uid":"5GFaH5","number":"#0126","squadron":"Squadron Wanus v30.81","highScore":167000,"rank":5,"width":800,"height":800},{"uid":"DtP2h7","number":"#0134","squadron":"Squadron Tetune","highScore":155900,"rank":5,"width":800,"height":800},{"uid":"qrJ6Ut","number":"#0003","squadron":"Squadron Tubos","highScore":128200,"rank":4,"width":800,"height":800},{"uid":"reRmdk","number":"#0059","squadron":"Squadron Qewei","highScore":112900,"rank":3,"width":800,"height":800},{"uid":"fcI60G","number":"#0061","squadron":"Squadron Wuturn v18.96","highScore":108300,"rank":3,"width":800,"height":800},{"uid":"5lU1oF","number":"#0009","squadron":"Squadron Relia v12.42","highScore":107900,"rank":3,"width":800,"height":800},{"uid":"MPqRhl","number":"#0066","squadron":"Squadron Ferilia","highScore":107900,"rank":3,"width":800,"height":800},{"uid":"tQrdtA","number":"#0022","squadron":"Squadron Yocarro Mk XLVII","highScore":107800,"rank":3,"width":800,"height":800},{"uid":"5UXHZh","number":"#0063","squadron":"Squadron Logawa","highScore":107800,"rank":3,"width":800,"height":800},{"uid":"HAaQDP","number":"#0025","squadron":"Squadron Iapra","highScore":103900,"rank":3,"width":800,"height":800},{"uid":"SJNnt4","number":"#0117","squadron":"Squadron Cethea","highScore":103800,"rank":3,"width":800,"height":800},{"uid":"hnkUk5","number":"#0143","squadron":"Squadron Ronope Mk LXVIII","highScore":103700,"rank":3,"width":800,"height":800},{"uid":"VmEp9z","number":"#0075","squadron":"Squadron Jenides","highScore":103300,"rank":3,"width":800,"height":800},{"uid":"vxujiE","number":"#0024","squadron":"Squadron Wehines Mk L","highScore":103200,"rank":3,"width":800,"height":800},{"uid":"StamY0","number":"#0039","squadron":"Squadron Cuvis","highScore":103200,"rank":3,"width":800,"height":800},{"uid":"93sIe2","number":"#0068","squadron":"Squadron Fucury","highScore":99800,"rank":3,"width":800,"height":800},{"uid":"9siPl4","number":"#0044","squadron":"Squadron Wunus","highScore":99200,"rank":3,"width":800,"height":800},{"uid":"hSBr2H","number":"#0084","squadron":"Squadron Iuzuno","highScore":99200,"rank":3,"width":800,"height":800},{"uid":"KL6G13","number":"#0097","squadron":"Squadron Foter","highScore":99200,"rank":3,"width":800,"height":800},{"uid":"ZPmeom","number":"#0016","squadron":"Squadron Purilia Mk XXXV","highScore":99100,"rank":3,"width":800,"height":800},{"uid":"SxH5K0","number":"#0006","squadron":"Squadron Sophus","highScore":98500,"rank":3,"width":800,"height":800},{"uid":"r8P0Ni","number":"#0008","squadron":"Squadron Tepra","highScore":98500,"rank":3,"width":800,"height":800},{"uid":"RLImcC","number":"#0099","squadron":"Squadron Vathea","highScore":98500,"rank":3,"width":800,"height":800},{"uid":"B0Nvsh","number":"#0100","squadron":"Squadron Turilia v28.53","highScore":98500,"rank":3,"width":800,"height":800},{"uid":"2fX1WG","number":"#0146","squadron":"Squadron Yonia","highScore":98100,"rank":3,"width":800,"height":800},{"uid":"cA1EQO","number":"#0005","squadron":"Squadron Cotania","highScore":97500,"rank":3,"width":800,"height":800},{"uid":"uWClzh","number":"#0015","squadron":"Squadron Honov","highScore":97500,"rank":3,"width":800,"height":800},{"uid":"1oIZmQ","number":"#0026","squadron":"Squadron Jolea","highScore":97500,"rank":3,"width":800,"height":800},{"uid":"t0hSH9","number":"#0065","squadron":"Squadron Huthea","highScore":97500,"rank":3,"width":800,"height":800},{"uid":"vaROvl","number":"#0109","squadron":"Squadron Ioliv","highScore":97500,"rank":3,"width":800,"height":800},{"uid":"2UaUWn","number":"#0011","squadron":"Squadron Wuwei v12.30","highScore":93400,"rank":3,"width":800,"height":800},{"uid":"IWbpKA","number":"#0018","squadron":"Squadron Buwei","highScore":93400,"rank":3,"width":800,"height":800},{"uid":"balDgT","number":"#0023","squadron":"Squadron Manope Mk XXXVII","highScore":93400,"rank":3,"width":800,"height":800},{"uid":"258TTE","number":"#0029","squadron":"Squadron Nehiri","highScore":93400,"rank":3,"width":800,"height":800},{"uid":"2SbiqP","number":"#0089","squadron":"Squadron Lanus","highScore":93400,"rank":3,"width":800,"height":800},{"uid":"vGw6VG","number":"#0040","squadron":"Squadron Wuter Mk XVII","highScore":92900,"rank":3,"width":800,"height":800},{"uid":"JzbzqY","number":"#0070","squadron":"Squadron Qunus","highScore":92400,"rank":3,"width":800,"height":800},{"uid":"mj0xMJ","number":"#0047","squadron":"Squadron Futis","highScore":88300,"rank":3,"width":800,"height":800},{"uid":"popkln","number":"#0054","squadron":"Squadron Halea v22.63","highScore":88300,"rank":3,"width":800,"height":800},{"uid":"sYwsmE","number":"#0069","squadron":"Squadron Bonope","highScore":88300,"rank":3,"width":800,"height":800},{"uid":"ouqM4C","number":"#0132","squadron":"Squadron Vetania","highScore":88300,"rank":3,"width":800,"height":800},{"uid":"HuSEHZ","number":"#0067","squadron":"Squadron Rozuno","highScore":83600,"rank":2,"width":800,"height":800},{"uid":"wWoVHI","number":"#0078","squadron":"Squadron Zuter","highScore":78200,"rank":2,"width":800,"height":800},{"uid":"z9Kqfc","number":"#0127","squadron":"Squadron Quwei","highScore":77900,"rank":2,"width":800,"height":800},{"uid":"NJb8BD","number":"#0032","squadron":"Squadron Later","highScore":77500,"rank":2,"width":800,"height":800},{"uid":"LQwTli","number":"#0033","squadron":"Squadron Lacarro","highScore":76000,"rank":2,"width":800,"height":800},{"uid":"FZ90KA","number":"#0079","squadron":"Squadron Dutune","highScore":76000,"rank":2,"width":800,"height":800},{"uid":"j8RJGv","number":"#0052","squadron":"Squadron Qustea","highScore":74400,"rank":2,"width":800,"height":800},{"uid":"EupY9l","number":"#0046","squadron":"Squadron Henerth Mk VIII","highScore":74200,"rank":2,"width":800,"height":800},{"uid":"Hng2xl","number":"#0115","squadron":"Squadron Lethea Mk XCVII","highScore":73000,"rank":2,"width":800,"height":800},{"uid":"FsxIku","number":"#0042","squadron":"Squadron Potera","highScore":72600,"rank":2,"width":800,"height":800},{"uid":"LsZCnK","number":"#0012","squadron":"Squadron Yutera Mk LXXXIV","highScore":72500,"rank":2,"width":800,"height":800},{"uid":"4XKSyK","number":"#0077","squadron":"Squadron Vucarro v33.11","highScore":72500,"rank":2,"width":800,"height":800},{"uid":"k2hg1Q","number":"#0004","squadron":"Squadron Pecury","highScore":62200,"rank":2,"width":800,"height":800},{"uid":"5AKIzS","number":"#0098","squadron":"Squadron Suria Mk XCVII","highScore":54200,"rank":1,"width":800,"height":800},{"uid":"ZPX4RU","number":"#0041","squadron":"Squadron Toliv v6.73","highScore":52800,"rank":1,"width":800,"height":800},{"uid":"mLmaRW","number":"#0073","squadron":"Squadron Vophus","highScore":48400,"rank":1,"width":800,"height":800},{"uid":"8yiSpg","number":"#0104","squadron":"Squadron Nutera","highScore":45100,"rank":1,"width":800,"height":800},{"uid":"gnYNkV","number":"#0121","squadron":"Squadron Sugantu","highScore":44900,"rank":1,"width":800,"height":800},{"uid":"Pda4kp","number":"#0131","squadron":"Squadron Iunus v35.24","highScore":43400,"rank":1,"width":800,"height":800},{"uid":"FzX600","number":"#0045","squadron":"Squadron Futer","highScore":38900,"rank":1,"width":800,"height":800},{"uid":"dUurgh","number":"#0014","squadron":"Squadron Qewei Mk XCV","highScore":32800,"rank":1,"width":800,"height":800},{"uid":"QtPoD8","number":"#0010","squadron":"Squadron Xocury","highScore":25000,"rank":0,"width":800,"height":800},{"uid":"O7rxW5","number":"#0093","squadron":"Squadron Megantu","highScore":23800,"rank":0,"width":800,"height":800},{"uid":"58L5iF","number":"#0038","squadron":"Squadron Selia","highScore":19600,"rank":0,"width":800,"height":800},{"uid":"l5DGHA","number":"#0141","squadron":"Squadron Quphus","highScore":19100,"rank":0,"width":800,"height":800},{"uid":"2sSF5t","number":"#0092","squadron":"Squadron Yestea","highScore":18800,"rank":0,"width":800,"height":800},{"uid":"VMUIFd","number":"#0086","squadron":"Squadron Peturn","highScore":15100,"rank":0,"width":800,"height":800},{"uid":"P6QvbE","number":"#0140","squadron":"Squadron Jeliv","highScore":15100,"rank":0,"width":800,"height":800},{"uid":"fsRGuA","number":"#0060","squadron":"Squadron Tonides","highScore":14500,"rank":0,"width":800,"height":800},{"uid":"1W0ajI","number":"#0050","squadron":"Squadron Dovis v46.22","highScore":13600,"rank":0,"width":800,"height":800},{"uid":"R4JAox","number":"#0101","squadron":"Squadron Fabos","highScore":10500,"rank":0,"width":800,"height":800},{"uid":"in9rqU","number":"#0139","squadron":"Squadron Konus Mk LVIII","highScore":9100,"rank":0,"width":800,"height":800},{"uid":"guzrdk","number":"#0027","squadron":"Squadron Yutania","highScore":9000,"rank":0,"width":800,"height":800},{"uid":"vy9JGd","number":"#0072","squadron":"Squadron Xulia","highScore":9000,"rank":0,"width":800,"height":800},{"uid":"A7qrc3","number":"#0051","squadron":"Squadron Xaturn","highScore":4800,"rank":0,"width":800,"height":800}]